README
setup.py
PyFixation.egg-info/PKG-INFO
PyFixation.egg-info/SOURCES.txt
PyFixation.egg-info/dependency_links.txt
PyFixation.egg-info/requires.txt
PyFixation.egg-info/top_level.txt
pyfixation/__init__.py
pyfixation/velocity.py