Metadata-Version: 1.1
Name: PyFixation
Version: 0.4.1
Summary: A library for online fixation processing
Home-page: https://github.com/RyanHope/PyFixation
Author: Ryan Hope
Author-email: rmh3093@gmail.com
License: GPL-3
Platform: UNKNOWN
Classifier: License :: OSI Approved :: GNU General Public License (GPL)
Classifier: Programming Language :: Python :: 2
Classifier: Topic :: Scientific/Engineering
Classifier: Topic :: Utilities
